pytopk/__init__.py
pytopk/functional.py
pytopk/noised_losses.py
pytopk/noised_topk.py
pytopk-0.1.0.dist-info/LICENSE
pytopk-0.1.0.dist-info/METADATA
pytopk-0.1.0.dist-info/WHEEL
pytopk-0.1.0.dist-info/top_level.txt
pytopk-0.1.0.dist-info/RECORD
