Metadata-Version: 2.1
Name: pytopk
Version: 0.1.0
Summary: Pytorch implementation of a differentiable topk function, a balanced and imbalanced top-k loss for deep learning
Home-page: https://github.com/garcinc/noised-topk
Author: Camille Garcin
License: MIT
Keywords: topk,deep learning,pytorch,differentiable
License-File: LICENSE
Requires-Dist: torch (>=1.0)
Requires-Dist: numpy
